elasticutils/estestcase.py
elasticutils/__init__.py
elasticutils/_version.py
elasticutils/utils.py
elasticutils/monkeypatch.py
elasticutils/contrib/__init__.py
elasticutils/contrib/django/estestcase.py
elasticutils/contrib/django/__init__.py
elasticutils/contrib/django/tasks.py
elasticutils/contrib/django/templates/elasticutils/501.html
elasticutils/contrib/django/templates/elasticutils/503.html
elasticutils/contrib/django/tests/test_utils.py
elasticutils/contrib/django/tests/test_tasks.py
elasticutils/contrib/django/tests/__init__.py
elasticutils/contrib/django/tests/test_middleware.py
elasticutils/contrib/django/tests/test_query.py
elasticutils/contrib/django/tests/test_models.py
elasticutils/contrib/django/tests/test_s.py
elasticutils/tests/__init__.py
elasticutils/tests/test_query.py
elasticutils/tests/test_es.py
elasticutils/tests/test_monkeypatch.py
elasticutils/tests/test_results.py
elasticutils/tests/test_utility_functions.py
elasticutils/tests/test_types.py
elasticutils/tests/test_mlt.py
elasticutils-0.10.3.dist-info/WHEEL
elasticutils-0.10.3.dist-info/top_level.txt
elasticutils-0.10.3.dist-info/RECORD
elasticutils-0.10.3.dist-info/METADATA
elasticutils-0.10.3.dist-info/metadata.json
elasticutils-0.10.3.dist-info/DESCRIPTION.rst
